chatapp_evaltools/__init__.py
chatapp_evaltools/__main__.py
chatapp_evaltools/cli.py
chatapp_evaltools/diff_app.py
chatapp_evaltools/diff_app.tcss
chatapp_evaltools/parameters_screen.tcss
chatapp_evaltools/summary_app.py
chatapp_evaltools-0.0.5.dist-info/METADATA
chatapp_evaltools-0.0.5.dist-info/WHEEL
chatapp_evaltools-0.0.5.dist-info/entry_points.txt
chatapp_evaltools-0.0.5.dist-info/top_level.txt
chatapp_evaltools-0.0.5.dist-info/RECORD
