Metadata-Version: 2.1
Name: chatapp-evaltools
Version: 0.0.5
Summary: Super generic evaluation tools for AI chat apps
Requires-Python: >=3.9
Requires-Dist: textual
Requires-Dist: typer
Provides-Extra: dev
Requires-Dist: pre-commit ; extra == 'dev'
Requires-Dist: ruff ; extra == 'dev'
Requires-Dist: black ; extra == 'dev'
Requires-Dist: pytest ; extra == 'dev'
Requires-Dist: coverage ; extra == 'dev'
Requires-Dist: pytest-cov ; extra == 'dev'
